setup.py
asynchttp/__init__.py
asynchttp.egg-info/PKG-INFO
asynchttp.egg-info/SOURCES.txt
asynchttp.egg-info/dependency_links.txt
asynchttp.egg-info/requires.txt
asynchttp.egg-info/top_level.txt