Metadata-Version: 1.1
Name: asynchttp
Version: 0.0.4
Summary: A simple httplib2 based asynchronous HTTP library for python
Home-page: http://github.com/ross/python-asynchttp
Author: Ross McFarland
Author-email: ross@gmail.com
License: UNKNOWN
Platform: UNKNOWN
Classifier: Development Status :: 4 - Beta
Classifier: Environment :: Console
Classifier: Environment :: Web Environment
Classifier: Intended Audience :: Developers
Classifier: Intended Audience :: Information Technology
Classifier: Operating System :: MacOS :: MacOS X
Classifier: Operating System :: POSIX
Classifier: Programming Language :: Python
Classifier: Topic :: Internet :: WWW/HTTP
Classifier: Topic :: Software Development :: Libraries :: Python Modules
Requires: httplib2(>=0.5.0)
Provides: asynchttp
